full_adder_3/full_adder.v
module full_adder(x, y, c_in, s, c_out);
	input x, y, c_in;
	output s, c_out;

	wire s1;

	assign #1 s1 = x ^ y;
	assign #1 s = s1 ^ c_in;
	assign #1 c_out = (s1 & c_in) | (x & y);
endmodule

1/full_adder_3/full_adder_3.v
module full_adder_3(x, y, c_in, s, c_out);
	input[2:0] x, y;
	input c_in;
	output[2:0] s;
	output c_out;

	wire c_in1;
	wire c_in2;

	// sfrutto il full adder già creato
	full_adder f0 (
		.x(x[0]), .y(y[0]), .c_in(c_in),
		.s(s[0]), .c_out(c_in1)
	);
	
	full_adder f1 (
		.x(x[1]), .y(y[0]), .c_in(c_in1),
		.s(s[1]), .c_out(c_in2) 
	);

	full_adder f2 (
		.x(x[2]), .y(y[2]), .c_in(c_in2),
		.s(s[2]), .c_out(c_out)
	);
	
endmodule

1/full_adder_3/testbench.v
module testbench();
    reg [2:0] x, y;
    reg c_in;
    wire [2:0] s;
    wire c_out;

    full_adder_3 fa (
        .x(x), .y(y), .c_in(c_in),
        .s(s), .c_out(c_out)
    );

    initial begin
        $dumpfile("waveform.vcd");
        $dumpvars;

        x = 3'b000;
        y = 3'b000;
        c_in = 0;
        #20;
        if(c_out == 0 && s == 3'b000)
            $display("000 000 0 -> 0 000 success");
        else
            $display("000 000 0 -> 0 000 fail");

        x = 3'b101;
        y = 3'b011;
        c_in = 0;   
        #20;
        if(c_out == 1 && s == 3'b000)
            $display("101 011 0 -> 1 000 success");
        else
            $display("101 011 0 -> 1 000 fail");

    end

endmodule

1/full_adder_3/waveform.vcd
$date
	Wed Nov 13 12:20:31 2024
$end
$version
	Icarus Verilog
$end
$timescale
	1s
$end
$scope module testbench $end
$var wire 3 ! s [2:0] $end
$var wire 1 " c_out $end
$var reg 1 # c_in $end
$var reg 3 $ x [2:0] $end
$var reg 3 % y [2:0] $end
$scope module fa $end
$var wire 1 # c_in $end
$var wire 3 & x [2:0] $end
$var wire 3 ' y [2:0] $end
$var wire 3 ( s [2:0] $end
$var wire 1 " c_out $end
$var wire 1 ) c_in2 $end
$var wire 1 * c_in1 $end
$scope module f0 $end
$var wire 1 # c_in $end
$var wire 1 * c_out $end
$var wire 1 + s $end
$var wire 1 , s1 $end
$var wire 1 - x $end
$var wire 1 . y $end
$upscope $end
$scope module f1 $end
$var wire 1 * c_in $end
$var wire 1 ) c_out $end
$var wire 1 / s $end
$var wire 1 0 s1 $end
$var wire 1 1 x $end
$var wire 1 2 y $end
$upscope $end
$scope module f2 $end
$var wire 1 ) c_in $end
$var wire 1 " c_out $end
$var wire 1 3 s $end
$var wire 1 4 s1 $end
$var wire 1 5 x $end
$var wire 1 6 y $end
$upscope $end
$upscope $end
$upscope $end
$enddefinitions $end
$comment Show the parameter values. $end
$dumpall
$end
#0
$dumpvars
06
05
x4
x3
02
01
x0
x/
0.
0-
x,
x+
x*
x)
bx (
b0 '
b0 &
b0 %
b0 $
0#
x"
bx !
$end
#1
0*
0,
00
04
#2
0)
0"
0+
bx00 !
bx00 (
0/
#3
b0 !
b0 (
03
#20
1.
12
1-
15
b11 %
b11 '
b101 $
b101 &
#21
1*
10
14
#22
1)
b100 !
b100 (
13
#23
1"
b0 !
b0 (
03
