3/perimetro/module.v
module ABC(a, b, p,
					 dav_, rfd,
					 clock, reset_);
	input[3:0] a, b;
	output[5:0] p;

	input dav_;
	output rfd;
	input clock, reset_;

	reg[6:0] P;
	assign p = P;

	reg RFD;
	assign rfd = RFD;

	reg[3:0] A, B;
	reg[2:0] STAR;
	localparam
		S0 = 0,
		S1 = 1,
		S2 = 2,
		S3 = 3;

	wire[5:0] out_rc;
	RC_PERIMETRO rc (
		.a(A), .b(B),
		.p(out_rc)
	);

	// handshake dav_/rfd
	// a riposo: dav_ = 1, rfd = 1
	// 1) dav_ = 0: dati pronti dal produttore
	// 2) rfd = 0: dati letti dal consumatore
	// 3) dav_ = 1: produttore riprende il dav_
	// 4) rfd = 1: consumatore riprende l'rfd

	always @(reset_ == 0) begin 
		P = 0;
		RFD = 1;
		STAR = S0;
	end

	always @(posedge clock) if(reset_ == 1) #2 begin 
		case (STAR)
			S0 : begin
				STAR <= (dav_ == 0) ? S1 : S0;
			end
			S1 : begin
				A <= a; B <= b;
				RFD <= 0;
				STAR <= S2;
			end
			S2 : begin
				P <= out_rc;
				STAR <= (dav_ == 1) ? S3 : S2;	
			end
			S3 : begin
				RFD <= 1;
				STAR <= S0;
			end
		endcase
	end
endmodule

module RC_PERIMETRO(a, b, p);
	input[3:0] a, b;
	output[5:0] p;

	assign p = (a + b) * 2;
endmodule

3/perimetro/testbench.v
module testbench();
    reg [3:0] a, b;
    reg reset_, dav_;

    wire clock, rfd;
    wire [5:0] p;

    clock_generator clk(
        .clock(clock)
    );

    ABC dut(
        .a(a), .b(b), .clock(clock), .reset_(reset_), .dav_(dav_),
        .p(p), .rfd(rfd)
    );

    // Debug variable, used to highlight points on the waveform
    reg error;

    initial begin
        $dumpfile("waveform.vcd");
        $dumpvars;

        //the following structure is used to wait for expected signals, and fail if too much time passes
        fork : f
            begin
                #100000;
                $display("Timeout - waiting for signal failed");
                disable f;
            end
        //actual tests start here
            begin
                //reset phase
                reset_ = 0; #(clk.HALF_PERIOD);
                dav_ = 1;
                reset_ = 1; #(clk.HALF_PERIOD);

                //clock e' all' edge negativo

                if(rfd != 1)
                    $display("rfd is not 1 after reset");
                    
                fork
                    begin: producer
                        reg [5:0] i;
                        reg [3:0] t_a, t_b;
                        reg [5:0] t_p;

                        for (i = 0; i < 32; i++) begin
                            {t_a, t_b, t_p}= get_testcase(i[4:0]);

                            #(2*clk.HALF_PERIOD);
                            a = t_a;
                            b = t_b;
                            #(2*clk.HALF_PERIOD);
                            dav_ = 0;

                            @(negedge rfd);
                            dav_ = 1; #1;
                            {a, b} = 8'bX;

                            @(posedge rfd);
                        end
                    end

                    begin: consumer
                        reg [5:0] i;
                        reg [3:0] t_a, t_b;
                        reg [5:0] t_p;

                        for (i = 0; i < 32; i++) begin
                            {t_a, t_b, t_p}= get_testcase(i[4:0]);

                            @(p);
                            if(p != t_p) begin
                                $display("Expected %d, received %d", t_p, p);
                                error = 1;
                            end
                        end
                    end
                join

                #10;
                disable f;
            end
        join

        $finish;
    end

    initial error = 0;
    always @(posedge error) #1
        error = 0;

    function automatic [13:0] get_testcase;
        input [4:0] i;

        reg [3:0] a, b;
        reg [5:0] p;

        begin
            a = i[4:1] + 3;
            b = i[3:0] + 1;
            p = 2 * (a + b);

            get_testcase = {a, b, p};
        end
    endfunction

endmodule

module clock_generator(
    clock
);
    output clock;

    parameter HALF_PERIOD = 5;

    reg CLOCK;
    assign clock = CLOCK;

    initial CLOCK <= 0;
    always #HALF_PERIOD CLOCK <= ~CLOCK;

endmodule

3/perimetro/waveform.vcd
$date
	Wed Nov 20 12:25:28 2024
$end
$version
	Icarus Verilog
$end
$timescale
	1s
$end
$scope module testbench $end
$var wire 1 ! rfd $end
$var wire 6 " p [5:0] $end
$var wire 1 # clock $end
$var reg 4 $ a [3:0] $end
$var reg 4 % b [3:0] $end
$var reg 1 & dav_ $end
$var reg 1 ' error $end
$var reg 1 ( reset_ $end
$scope function get_testcase $end
$upscope $end
$scope module clk $end
$var wire 1 # clock $end
$var parameter 32 ) HALF_PERIOD $end
$var reg 1 * CLOCK $end
$upscope $end
$scope module dut $end
$var wire 4 + a [3:0] $end
$var wire 4 , b [3:0] $end
$var wire 1 # clock $end
$var wire 1 & dav_ $end
$var wire 1 ( reset_ $end
$var wire 1 ! rfd $end
$var wire 6 - p [5:0] $end
$var wire 6 . out_rc [5:0] $end
$var parameter 32 / S0 $end
$var parameter 32 0 S1 $end
$var parameter 32 1 S2 $end
$var parameter 32 2 S3 $end
$var reg 4 3 A [3:0] $end
$var reg 4 4 B [3:0] $end
$var reg 7 5 P [6:0] $end
$var reg 1 6 RFD $end
$var reg 3 7 STAR [2:0] $end
$scope module rc $end
$var wire 4 8 a [3:0] $end
$var wire 4 9 b [3:0] $end
$var wire 6 : p [5:0] $end
$upscope $end
$upscope $end
$scope fork f $end
$scope begin consumer $end
$var reg 6 ; i [5:0] $end
$var reg 4 < t_a [3:0] $end
$var reg 4 = t_b [3:0] $end
$var reg 6 > t_p [5:0] $end
$upscope $end
$scope begin producer $end
$var reg 6 ? i [5:0] $end
$var reg 4 @ t_a [3:0] $end
$var reg 4 A t_b [3:0] $end
$var reg 6 B t_p [5:0] $end
$upscope $end
$upscope $end
$upscope $end
$enddefinitions $end
$comment Show the parameter values. $end
$dumpall
b11 2
b10 1
b1 0
b0 /
b101 )
$end
#0
$dumpvars
bx B
bx A
bx @
bx ?
bx >
bx =
bx <
bx ;
bx :
bx 9
bx 8
b0 7
16
b0 5
bx 4
bx 3
bx .
b0 -
bx ,
bx +
0*
0(
0'
x&
bx %
bx $
0#
b0 "
1!
$end
#5
1#
1*
1(
1&
#10
0#
0*
b11 @
b1 A
b1000 B
b0 ?
b11 <
b1 =
b1000 >
b0 ;
#15
1#
1*
#20
0#
0*
b1 %
b1 ,
b11 $
b11 +
#25
1#
1*
#30
0#
0*
0&
#35
1#
1*
#37
b1 7
#40
0#
0*
#45
1#
1*
#47
1&
b10 7
0!
06
b1000 .
b1000 :
b1 4
b1 9
b11 3
b11 8
#48
bx $
bx +
bx %
bx ,
#50
0#
0*
#55
1#
1*
#57
b10 =
b1010 >
b1 ;
b1000 "
b1000 -
b11 7
b1000 5
#60
0#
0*
#65
1#
1*
#67
b10 A
b1010 B
b1 ?
b0 7
1!
16
#70
0#
0*
#75
1#
1*
#77
b10 %
b10 ,
b11 $
b11 +
#80
0#
0*
#85
1#
1*
#87
b1 7
0&
#90
0#
0*
#95
1#
1*
#97
1&
b10 7
0!
06
b1010 .
b1010 :
b10 4
b10 9
#98
bx $
bx +
bx %
bx ,
#100
0#
0*
#105
1#
1*
#107
b100 <
b11 =
b1110 >
b10 ;
b1010 "
b1010 -
b11 7
b1010 5
#110
0#
0*
#115
1#
1*
#117
b100 @
b11 A
b1110 B
b10 ?
b0 7
1!
16
#120
0#
0*
#125
1#
1*
#127
b11 %
b11 ,
b100 $
b100 +
#130
0#
0*
#135
1#
1*
#137
b1 7
0&
#140
0#
0*
#145
1#
1*
#147
1&
b10 7
0!
06
b11 4
b11 9
b1110 .
b1110 :
b100 3
b100 8
#148
bx $
bx +
bx %
bx ,
#150
0#
0*
#155
1#
1*
#157
b100 =
b10000 >
b11 ;
b1110 "
b1110 -
b11 7
b1110 5
#160
0#
0*
#165
1#
1*
#167
b100 A
b10000 B
b11 ?
b0 7
1!
16
#170
0#
0*
#175
1#
1*
#177
b100 %
b100 ,
b100 $
b100 +
#180
0#
0*
#185
1#
1*
#187
b1 7
0&
#190
0#
0*
#195
1#
1*
#197
1&
b10 7
0!
06
b10000 .
b10000 :
b100 4
b100 9
#198
bx $
bx +
bx %
bx ,
#200
0#
0*
#205
1#
1*
#207
b101 <
b101 =
b10100 >
b100 ;
b10000 "
b10000 -
b11 7
b10000 5
#210
0#
0*
#215
1#
1*
#217
b101 @
b101 A
b10100 B
b100 ?
b0 7
1!
16
#220
0#
0*
#225
1#
1*
#227
b101 %
b101 ,
b101 $
b101 +
#230
0#
0*
#235
1#
1*
#237
b1 7
0&
#240
0#
0*
#245
1#
1*
#247
1&
b10 7
0!
06
b101 4
b101 9
b10100 .
b10100 :
b101 3
b101 8
#248
bx $
bx +
bx %
bx ,
#250
0#
0*
#255
1#
1*
#257
b110 =
b10110 >
b101 ;
b10100 "
b10100 -
b11 7
b10100 5
#260
0#
0*
#265
1#
1*
#267
b110 A
b10110 B
b101 ?
b0 7
1!
16
#270
0#
0*
#275
1#
1*
#277
b110 %
b110 ,
b101 $
b101 +
#280
0#
0*
#285
1#
1*
#287
b1 7
0&
#290
0#
0*
#295
1#
1*
#297
1&
b10 7
0!
06
b10110 .
b10110 :
b110 4
b110 9
#298
bx $
bx +
bx %
bx ,
#300
0#
0*
#305
1#
1*
#307
b110 <
b111 =
b11010 >
b110 ;
b10110 "
b10110 -
b11 7
b10110 5
#310
0#
0*
#315
1#
1*
#317
b110 @
b111 A
b11010 B
b110 ?
b0 7
1!
16
#320
0#
0*
#325
1#
1*
#327
b111 %
b111 ,
b110 $
b110 +
#330
0#
0*
#335
1#
1*
#337
b1 7
0&
#340
0#
0*
#345
1#
1*
#347
1&
b10 7
0!
06
b111 4
b111 9
b11010 .
b11010 :
b110 3
b110 8
#348
bx $
bx +
bx %
bx ,
#350
0#
0*
#355
1#
1*
#357
b1000 =
b11100 >
b111 ;
b11010 "
b11010 -
b11 7
b11010 5
#360
0#
0*
#365
1#
1*
#367
b1000 A
b11100 B
b111 ?
b0 7
1!
16
#370
0#
0*
#375
1#
1*
#377
b1000 %
b1000 ,
b110 $
b110 +
#380
0#
0*
#385
1#
1*
#387
b1 7
0&
#390
0#
0*
#395
1#
1*
#397
1&
b10 7
0!
06
b11100 .
b11100 :
b1000 4
b1000 9
#398
bx $
bx +
bx %
bx ,
#400
0#
0*
#405
1#
1*
#407
b111 <
b1001 =
b100000 >
b1000 ;
b11100 "
b11100 -
b11 7
b11100 5
#410
0#
0*
#415
1#
1*
#417
b111 @
b1001 A
b100000 B
b1000 ?
b0 7
1!
16
#420
0#
0*
#425
1#
1*
#427
b1001 %
b1001 ,
b111 $
b111 +
#430
0#
0*
#435
1#
1*
#437
b1 7
0&
#440
0#
0*
#445
1#
1*
#447
1&
b10 7
0!
06
b1001 4
b1001 9
b100000 .
b100000 :
b111 3
b111 8
#448
bx $
bx +
bx %
bx ,
#450
0#
0*
#455
1#
1*
#457
b1010 =
b100010 >
b1001 ;
b100000 "
b100000 -
b11 7
b100000 5
#460
0#
0*
#465
1#
1*
#467
b1010 A
b100010 B
b1001 ?
b0 7
1!
16
#470
0#
0*
#475
1#
1*
#477
b1010 %
b1010 ,
b111 $
b111 +
#480
0#
0*
#485
1#
1*
#487
b1 7
0&
#490
0#
0*
#495
1#
1*
#497
1&
b10 7
0!
06
b100010 .
b100010 :
b1010 4
b1010 9
#498
bx $
bx +
bx %
bx ,
#500
0#
0*
#505
1#
1*
#507
b1000 <
b1011 =
b100110 >
b1010 ;
b100010 "
b100010 -
b11 7
b100010 5
#510
0#
0*
#515
1#
1*
#517
b1000 @
b1011 A
b100110 B
b1010 ?
b0 7
1!
16
#520
0#
0*
#525
1#
1*
#527
b1011 %
b1011 ,
b1000 $
b1000 +
#530
0#
0*
#535
1#
1*
#537
b1 7
0&
#540
0#
0*
#545
1#
1*
#547
1&
b10 7
0!
06
b1011 4
b1011 9
b100110 .
b100110 :
b1000 3
b1000 8
#548
bx $
bx +
bx %
bx ,
#550
0#
0*
#555
1#
1*
#557
b1100 =
b101000 >
b1011 ;
b100110 "
b100110 -
b11 7
b100110 5
#560
0#
0*
#565
1#
1*
#567
b1100 A
b101000 B
b1011 ?
b0 7
1!
16
#570
0#
0*
#575
1#
1*
#577
b1100 %
b1100 ,
b1000 $
b1000 +
#580
0#
0*
#585
1#
1*
#587
b1 7
0&
#590
0#
0*
#595
1#
1*
#597
1&
b10 7
0!
06
b101000 .
b101000 :
b1100 4
b1100 9
#598
bx $
bx +
bx %
bx ,
#600
0#
0*
#605
1#
1*
#607
b1001 <
b1101 =
b101100 >
b1100 ;
b101000 "
b101000 -
b11 7
b101000 5
#610
0#
0*
#615
1#
1*
#617
b1001 @
b1101 A
b101100 B
b1100 ?
b0 7
1!
16
#620
0#
0*
#625
1#
1*
#627
b1101 %
b1101 ,
b1001 $
b1001 +
#630
0#
0*
#635
1#
1*
#637
b1 7
0&
#640
0#
0*
#645
1#
1*
#647
1&
b10 7
0!
06
b1101 4
b1101 9
b101100 .
b101100 :
b1001 3
b1001 8
#648
bx $
bx +
bx %
bx ,
#650
0#
0*
#655
1#
1*
#657
b1110 =
b101110 >
b1101 ;
b101100 "
b101100 -
b11 7
b101100 5
#660
0#
0*
#665
1#
1*
#667
b1110 A
b101110 B
b1101 ?
b0 7
1!
16
#670
0#
0*
#675
1#
1*
#677
b1110 %
b1110 ,
b1001 $
b1001 +
#680
0#
0*
#685
1#
1*
#687
b1 7
0&
#690
0#
0*
#695
1#
1*
#697
1&
b10 7
0!
06
b101110 .
b101110 :
b1110 4
b1110 9
#698
bx $
bx +
bx %
bx ,
#700
0#
0*
#705
1#
1*
#707
b1010 <
b1111 =
b110010 >
b1110 ;
b101110 "
b101110 -
b11 7
b101110 5
#710
0#
0*
#715
1#
1*
#717
b1010 @
b1111 A
b110010 B
b1110 ?
b0 7
1!
16
#720
0#
0*
#725
1#
1*
#727
b1111 %
b1111 ,
b1010 $
b1010 +
#730
0#
0*
#735
1#
1*
#737
b1 7
0&
#740
0#
0*
#745
1#
1*
#747
1&
b10 7
0!
06
b1111 4
b1111 9
b110010 .
b110010 :
b1010 3
b1010 8
#748
bx $
bx +
bx %
bx ,
#750
0#
0*
#755
1#
1*
#757
b0 =
b10100 >
b1111 ;
b110010 "
b110010 -
b11 7
b110010 5
#760
0#
0*
#765
1#
1*
#767
b0 A
b10100 B
b1111 ?
b0 7
1!
16
#770
0#
0*
#775
1#
1*
#777
b0 %
b0 ,
b1010 $
b1010 +
#780
0#
0*
#785
1#
1*
#787
b1 7
0&
#790
0#
0*
#795
1#
1*
#797
1&
b10 7
0!
06
b10100 .
b10100 :
b0 4
b0 9
#798
bx $
bx +
bx %
bx ,
#800
0#
0*
#805
1#
1*
#807
b1011 <
b1 =
b11000 >
b10000 ;
b10100 "
b10100 -
b11 7
b10100 5
#810
0#
0*
#815
1#
1*
#817
b1011 @
b1 A
b11000 B
b10000 ?
b0 7
1!
16
#820
0#
0*
#825
1#
1*
#827
b1 %
b1 ,
b1011 $
b1011 +
#830
0#
0*
#835
1#
1*
#837
b1 7
0&
#840
0#
0*
#845
1#
1*
#847
1&
b10 7
0!
06
b1 4
b1 9
b11000 .
b11000 :
b1011 3
b1011 8
#848
bx $
bx +
bx %
bx ,
#850
0#
0*
#855
1#
1*
#857
b10 =
b11010 >
b10001 ;
b11000 "
b11000 -
b11 7
b11000 5
#860
0#
0*
#865
1#
1*
#867
b10 A
b11010 B
b10001 ?
b0 7
1!
16
#870
0#
0*
#875
1#
1*
#877
b10 %
b10 ,
b1011 $
b1011 +
#880
0#
0*
#885
1#
1*
#887
b1 7
0&
#890
0#
0*
#895
1#
1*
#897
1&
b10 7
0!
06
b11010 .
b11010 :
b10 4
b10 9
#898
bx $
bx +
bx %
bx ,
#900
0#
0*
#905
1#
1*
#907
b1100 <
b11 =
b11110 >
b10010 ;
b11010 "
b11010 -
b11 7
b11010 5
#910
0#
0*
#915
1#
1*
#917
b1100 @
b11 A
b11110 B
b10010 ?
b0 7
1!
16
#920
0#
0*
#925
1#
1*
#927
b11 %
b11 ,
b1100 $
b1100 +
#930
0#
0*
#935
1#
1*
#937
b1 7
0&
#940
0#
0*
#945
1#
1*
#947
1&
b10 7
0!
06
b11 4
b11 9
b11110 .
b11110 :
b1100 3
b1100 8
#948
bx $
bx +
bx %
bx ,
#950
0#
0*
#955
1#
1*
#957
b100 =
b100000 >
b10011 ;
b11110 "
b11110 -
b11 7
b11110 5
#960
0#
0*
#965
1#
1*
#967
b100 A
b100000 B
b10011 ?
b0 7
1!
16
#970
0#
0*
#975
1#
1*
#977
b100 %
b100 ,
b1100 $
b1100 +
#980
0#
0*
#985
1#
1*
#987
b1 7
0&
#990
0#
0*
#995
1#
1*
#997
1&
b10 7
0!
06
b100000 .
b100000 :
b100 4
b100 9
#998
bx $
bx +
bx %
bx ,
#1000
0#
0*
#1005
1#
1*
#1007
b1101 <
b101 =
b100100 >
b10100 ;
b100000 "
b100000 -
b11 7
b100000 5
#1010
0#
0*
#1015
1#
1*
#1017
b1101 @
b101 A
b100100 B
b10100 ?
b0 7
1!
16
#1020
0#
0*
#1025
1#
1*
#1027
b101 %
b101 ,
b1101 $
b1101 +
#1030
0#
0*
#1035
1#
1*
#1037
b1 7
0&
#1040
0#
0*
#1045
1#
1*
#1047
1&
b10 7
0!
06
b101 4
b101 9
b100100 .
b100100 :
b1101 3
b1101 8
#1048
bx $
bx +
bx %
bx ,
#1050
0#
0*
#1055
1#
1*
#1057
b110 =
b100110 >
b10101 ;
b100100 "
b100100 -
b11 7
b100100 5
#1060
0#
0*
#1065
1#
1*
#1067
b110 A
b100110 B
b10101 ?
b0 7
1!
16
#1070
0#
0*
#1075
1#
1*
#1077
b110 %
b110 ,
b1101 $
b1101 +
#1080
0#
0*
#1085
1#
1*
#1087
b1 7
0&
#1090
0#
0*
#1095
1#
1*
#1097
1&
b10 7
0!
06
b100110 .
b100110 :
b110 4
b110 9
#1098
bx $
bx +
bx %
bx ,
#1100
0#
0*
#1105
1#
1*
#1107
b1110 <
b111 =
b101010 >
b10110 ;
b100110 "
b100110 -
b11 7
b100110 5
#1110
0#
0*
#1115
1#
1*
#1117
b1110 @
b111 A
b101010 B
b10110 ?
b0 7
1!
16
#1120
0#
0*
#1125
1#
1*
#1127
b111 %
b111 ,
b1110 $
b1110 +
#1130
0#
0*
#1135
1#
1*
#1137
b1 7
0&
#1140
0#
0*
#1145
1#
1*
#1147
1&
b10 7
0!
06
b111 4
b111 9
b101010 .
b101010 :
b1110 3
b1110 8
#1148
bx $
bx +
bx %
bx ,
#1150
0#
0*
#1155
1#
1*
#1157
b1000 =
b101100 >
b10111 ;
b101010 "
b101010 -
b11 7
b101010 5
#1160
0#
0*
#1165
1#
1*
#1167
b1000 A
b101100 B
b10111 ?
b0 7
1!
16
#1170
0#
0*
#1175
1#
1*
#1177
b1000 %
b1000 ,
b1110 $
b1110 +
#1180
0#
0*
#1185
1#
1*
#1187
b1 7
0&
#1190
0#
0*
#1195
1#
1*
#1197
1&
b10 7
0!
06
b101100 .
b101100 :
b1000 4
b1000 9
#1198
bx $
bx +
bx %
bx ,
#1200
0#
0*
#1205
1#
1*
#1207
b1111 <
b1001 =
b110000 >
b11000 ;
b101100 "
b101100 -
b11 7
b101100 5
#1210
0#
0*
#1215
1#
1*
#1217
b1111 @
b1001 A
b110000 B
b11000 ?
b0 7
1!
16
#1220
0#
0*
#1225
1#
1*
#1227
b1001 %
b1001 ,
b1111 $
b1111 +
#1230
0#
0*
#1235
1#
1*
#1237
b1 7
0&
#1240
0#
0*
#1245
1#
1*
#1247
1&
b10 7
0!
06
b1001 4
b1001 9
b110000 .
b110000 :
b1111 3
b1111 8
#1248
bx $
bx +
bx %
bx ,
#1250
0#
0*
#1255
1#
1*
#1257
b1010 =
b110010 >
b11001 ;
b110000 "
b110000 -
b11 7
b110000 5
#1260
0#
0*
#1265
1#
1*
#1267
b1010 A
b110010 B
b11001 ?
b0 7
1!
16
#1270
0#
0*
#1275
1#
1*
#1277
b1010 %
b1010 ,
b1111 $
b1111 +
#1280
0#
0*
#1285
1#
1*
#1287
b1 7
0&
#1290
0#
0*
#1295
1#
1*
#1297
1&
b10 7
0!
06
b110010 .
b110010 :
b1010 4
b1010 9
#1298
bx $
bx +
bx %
bx ,
#1300
0#
0*
#1305
1#
1*
#1307
b0 <
b1011 =
b10110 >
b11010 ;
b110010 "
b110010 -
b11 7
b110010 5
#1310
0#
0*
#1315
1#
1*
#1317
b0 @
b1011 A
b10110 B
b11010 ?
b0 7
1!
16
#1320
0#
0*
#1325
1#
1*
#1327
b1011 %
b1011 ,
b0 $
b0 +
#1330
0#
0*
#1335
1#
1*
#1337
b1 7
0&
#1340
0#
0*
#1345
1#
1*
#1347
1&
b10 7
0!
06
b1011 4
b1011 9
b10110 .
b10110 :
b0 3
b0 8
#1348
bx $
bx +
bx %
bx ,
#1350
0#
0*
#1355
1#
1*
#1357
b1100 =
b11000 >
b11011 ;
b10110 "
b10110 -
b11 7
b10110 5
#1360
0#
0*
#1365
1#
1*
#1367
b1100 A
b11000 B
b11011 ?
b0 7
1!
16
#1370
0#
0*
#1375
1#
1*
#1377
b1100 %
b1100 ,
b0 $
b0 +
#1380
0#
0*
#1385
1#
1*
#1387
b1 7
0&
#1390
0#
0*
#1395
1#
1*
#1397
1&
b10 7
0!
06
b11000 .
b11000 :
b1100 4
b1100 9
#1398
bx $
bx +
bx %
bx ,
#1400
0#
0*
#1405
1#
1*
#1407
b1 <
b1101 =
b11100 >
b11100 ;
b11000 "
b11000 -
b11 7
b11000 5
#1410
0#
0*
#1415
1#
1*
#1417
b1 @
b1101 A
b11100 B
b11100 ?
b0 7
1!
16
#1420
0#
0*
#1425
1#
1*
#1427
b1101 %
b1101 ,
b1 $
b1 +
#1430
0#
0*
#1435
1#
1*
#1437
b1 7
0&
#1440
0#
0*
#1445
1#
1*
#1447
1&
b10 7
0!
06
b1101 4
b1101 9
b11100 .
b11100 :
b1 3
b1 8
#1448
bx $
bx +
bx %
bx ,
#1450
0#
0*
#1455
1#
1*
#1457
b1110 =
b11110 >
b11101 ;
b11100 "
b11100 -
b11 7
b11100 5
#1460
0#
0*
#1465
1#
1*
#1467
b1110 A
b11110 B
b11101 ?
b0 7
1!
16
#1470
0#
0*
#1475
1#
1*
#1477
b1110 %
b1110 ,
b1 $
b1 +
#1480
0#
0*
#1485
1#
1*
#1487
b1 7
0&
#1490
0#
0*
#1495
1#
1*
#1497
1&
b10 7
0!
06
b11110 .
b11110 :
b1110 4
b1110 9
#1498
bx $
bx +
bx %
bx ,
#1500
0#
0*
#1505
1#
1*
#1507
b10 <
b1111 =
b100010 >
b11110 ;
b11110 "
b11110 -
b11 7
b11110 5
#1510
0#
0*
#1515
1#
1*
#1517
b10 @
b1111 A
b100010 B
b11110 ?
b0 7
1!
16
#1520
0#
0*
#1525
1#
1*
#1527
b1111 %
b1111 ,
b10 $
b10 +
#1530
0#
0*
#1535
1#
1*
#1537
b1 7
0&
#1540
0#
0*
#1545
1#
1*
#1547
1&
b10 7
0!
06
b1111 4
b1111 9
b100010 .
b100010 :
b10 3
b10 8
#1548
bx $
bx +
bx %
bx ,
#1550
0#
0*
#1555
1#
1*
#1557
b0 =
b100 >
b11111 ;
b100010 "
b100010 -
b11 7
b100010 5
#1560
0#
0*
#1565
1#
1*
#1567
b0 A
b100 B
b11111 ?
b0 7
1!
16
#1570
0#
0*
#1575
1#
1*
#1577
b0 %
b0 ,
b10 $
b10 +
#1580
0#
0*
#1585
1#
1*
#1587
b1 7
0&
#1590
0#
0*
#1595
1#
1*
#1597
1&
b10 7
0!
06
b100 .
b100 :
b0 4
b0 9
#1598
bx $
bx +
bx %
bx ,
#1600
0#
0*
#1605
1#
1*
#1607
b100000 ;
b100 "
b100 -
b11 7
b100 5
#1610
0#
0*
#1615
1#
1*
#1617
b100000 ?
b0 7
1!
16
