intro/rc.v
module rc(x, y, z, w);
	input x, y;
	output w, z;

	assign #1 w = x & y;
	assign #2 z = x | y;
endmodule

1/intro/testbench.v
module testbench();
	reg t_x, t_y;
	wire t_w, t_z;

	rc dut (
		.x(t_x), .y(t_y),
		.w(t_w), .z(t_z)
	);

	initial begin
		// per gtkwave
		$dumpfile("waveform.vcd");
		$dumpvars;
		
		// qui va la sequenza del testbench
		// x:0 e y:0 -> z:0 e w:0 
		$display("Test x:0 e y:0 -> z:0 e w:0");
		t_x = 0;
		t_y = 0;

		#10; //aspetta

		if(t_z == 0 && t_w == 0)
			$display("Ok!");
		else
			$display("Questo male...");

		// x:1 e y:0 -> z:1 e w:0 
		$display("Test x:1 e y:0 -> z:1 e w:0");
		t_x = 1;
		t_y = 0;

		#10; //aspetta

		if(t_z == 1 && t_w == 0)
			$display("Ok!");
		else
			$display("Questo male...");

		// x:0 e y:1 -> z:1 e w:0 
		$display("Test x:0 e y:1 -> z:1 e w:0");
		t_x = 0;
		t_y = 1;

		#10; //aspetta

		if(t_z == 1 && t_w == 0)
			$display("Ok!");
		else
			$display("Questo male...");

		// x:1 e y:1 -> z:1 e w:1 
		$display("Test x:1 e y:1 -> z:1 e w:1");
		t_x = 1;
		t_y = 1;

		#10; //aspetta

		if(t_z == 1 && t_w == 1)
			$display("Ok!");
		else
			$display("Questo male...");

		//chiudi
		$finish;

 	end

endmodule

1/intro/waveform.vcd
$date
	Wed Nov 13 11:52:36 2024
$end
$version
	Icarus Verilog
$end
$timescale
	1s
$end
$scope module testbench $end
$var wire 1 ! t_z $end
$var wire 1 " t_w $end
$var reg 1 # t_x $end
$var reg 1 $ t_y $end
$scope module dut $end
$var wire 1 " w $end
$var wire 1 # x $end
$var wire 1 $ y $end
$var wire 1 ! z $end
$upscope $end
$upscope $end
$enddefinitions $end
$comment Show the parameter values. $end
$dumpall
$end
#0
$dumpvars
0$
0#
x"
x!
$end
#1
0"
#2
0!
#10
1#
#12
1!
#20
1$
0#
#30
1#
#31
1"
