misc/impulse_generator_soc_eoc/mprogram_synthesis.v
// un "generatore di impulsi" che legge da @numero attraverso un handshake soc-eoc, e genera un segnale
// alto per @numero cicli di clock
module impulse_generator(reset_, clock, numero, out, soc, eoc);
	input reset_, clock;
	input[7:0] numero;
	output out;
	output soc;
	input eoc;
	
	data_path dp(reset_, clock, numero, out, soc, eoc, b1, b0, c1, c0);
	control_unit cu(reset_, clock, b1, b0, c1, c0);
endmodule

module data_path(reset_, clock, numero, out, soc, eoc, b1, b0, c1, c0);
	input reset_, clock;
	input[7:0] numero;
	output out;
	output soc;
	input eoc;

	input b1, b0;
	output c1, c0;

	reg[7:0] COUNT;

	reg SOC;
	assign soc = SOC;
	
	reg OUT;
	assign out = OUT;

	always @(reset_ == 0) #1 begin
		SOC <= 0;
		OUT <= 0;
	end

	always @(posedge clock) if(reset_ == 1) #3 begin
		casex({b1, b0})
			'B?0: begin
				COUNT <= COUNT;
				SOC <= 1;
				OUT <= 0;
			end
			'B01: begin
				COUNT <= numero;
				SOC <= 0;
				OUT <= OUT;
			end
			'B11: begin
				COUNT <= COUNT - 1;
				SOC <= SOC;
				OUT <= 1;
			end
		endcase
	end

	assign c0 = eoc == 1;
	assign c1 = COUNT == 1;
endmodule

module control_unit(reset_, clock, b1, b0, c1, c0);
	input reset_, clock;

	output b1, b0;
	input c1, c0;

	reg[1:0] STAR;
	localparam
		s0 = 'B00,
		s1 = 'B01,
		s2 = 'B10;

	always @(reset_ == 0) #3 begin
		STAR <= s0;
	end

	// --- ROM ---
	wire m_b1 [0:3];
	wire m_b0 [0:3];
	wire eff [0:3];
	wire[1:0] addr_T [0:3];
	wire[1:0] addr_F [0:3];

	
	assign m_b1[0] = 'BX;
	assign m_b1[1] = 'B0;
	assign m_b1[2] = 'B1;
	
	assign m_b0[0] = 'B0;
	assign m_b0[1] = 'B1;
	assign m_b0[2] = 'B1;

	assign eff[0] = 'B0;
	assign eff[1] = 'B0;
	assign eff[2] = 'B1;

	assign addr_T[0] = 'B00;
	assign addr_T[1] = 'B10;
	assign addr_T[2] = 'B00;
	
	assign addr_F[0] = 'B01;
	assign addr_F[1] = 'B01;
	assign addr_F[2] = 'B10;
	// -----------
		
	assign b1 = m_b1[STAR];
	assign b0 = m_b0[STAR];

	wire c_eff;
	assign c_eff = eff[STAR] ? c1 : c0;

	wire[1:0] addr_N;
	assign addr_N = c_eff ? addr_T[STAR] : addr_F[STAR];

	always @(posedge clock) if(reset_ == 1) #3 begin
		STAR <= addr_N;
	end
endmodule

misc/impulse_generator_soc_eoc/testbench.v
module testbench();
	reg t_reset_, t_clock;
	reg[7:0] t_numero;
	reg t_eoc;

	wire t_out;
	wire t_soc;

	impulse_generator impulse_gen (
		.reset_(t_reset_), .clock(t_clock),
		.numero(t_numero), .out(t_out),
		.eoc(t_eoc), .soc(t_soc)
	);

	initial forever #5 t_clock = ~t_clock;

	initial begin
		$dumpfile("waveform.vcd");
		$dumpvars;

		t_clock = 0;
		t_reset_ = 1;
		t_eoc = 1;

		t_numero = 10;
	
		#10;
	
		t_eoc = 0;
	
		#20;
		
		t_eoc = 1;
		
		#200;

		t_numero = 5;
		
		#10;

		t_eoc = 0;

		#20;

		t_eoc = 1;

		#100;

		$finish;
	end
endmodule

misc/impulse_generator_soc_eoc/waveform.vcd
$date
	Sun Jan  5 12:41:13 2025
$end
$version
	Icarus Verilog
$end
$timescale
	1s
$end
$scope module testbench $end
$var wire 1 ! t_soc $end
$var wire 1 " t_out $end
$var reg 1 # t_clock $end
$var reg 1 $ t_eoc $end
$var reg 8 % t_numero [7:0] $end
$var reg 1 & t_reset_ $end
$scope module impulse_gen $end
$var wire 1 # clock $end
$var wire 1 $ eoc $end
$var wire 8 ' numero [7:0] $end
$var wire 1 & reset_ $end
$var wire 1 ! soc $end
$var wire 1 " out $end
$var wire 1 ( c1 $end
$var wire 1 ) c0 $end
$var wire 1 * b1 $end
$var wire 1 + b0 $end
$scope module cu $end
$var wire 1 + b0 $end
$var wire 1 * b1 $end
$var wire 1 # clock $end
$var wire 1 & reset_ $end
$var wire 1 , c_eff $end
$var wire 1 ( c1 $end
$var wire 1 ) c0 $end
$var wire 2 - addr_N [1:0] $end
$var parameter 32 . s0 $end
$var parameter 32 / s1 $end
$var parameter 32 0 s2 $end
$var reg 2 1 STAR [1:0] $end
$upscope $end
$scope module dp $end
$var wire 1 + b0 $end
$var wire 1 * b1 $end
$var wire 1 # clock $end
$var wire 1 $ eoc $end
$var wire 8 2 numero [7:0] $end
$var wire 1 " out $end
$var wire 1 & reset_ $end
$var wire 1 ! soc $end
$var wire 1 ( c1 $end
$var wire 1 ) c0 $end
$var reg 8 3 COUNT [7:0] $end
$var reg 1 4 OUT $end
$var reg 1 5 SOC $end
$upscope $end
$upscope $end
$upscope $end
$enddefinitions $end
$comment Show the parameter values. $end
$dumpall
b10 0
b1 /
b0 .
$end
#0
$dumpvars
x5
x4
bx 3
b1010 2
bx 1
bx -
x,
x+
x*
1)
x(
b1010 '
1&
b1010 %
1$
0#
x"
x!
$end
#1
0"
04
0!
05
#3
1,
b0 -
0+
b0 1
#5
1#
#8
1!
15
#10
b1 -
0,
0#
0)
0$
#15
1#
#18
0*
1+
b1 1
#20
0#
#25
1#
#28
0!
05
0(
b1010 3
#30
b10 -
1,
0#
1)
1$
#35
1#
#38
0,
b10 -
1*
b10 1
#40
0#
#45
1#
#48
1"
14
b1001 3
#50
0#
#55
1#
#58
b1000 3
#60
0#
#65
1#
#68
b111 3
#70
0#
#75
1#
#78
b110 3
#80
0#
#85
1#
#88
b101 3
#90
0#
#95
1#
#98
b100 3
#100
0#
#105
1#
#108
b11 3
#110
0#
#115
1#
#118
b10 3
#120
0#
#125
1#
#128
b0 -
1,
1(
b1 3
#130
0#
#135
1#
#138
x*
0+
b0 1
0(
b0 3
#140
0#
#145
1#
#148
0"
04
1!
15
#150
0#
#155
1#
#160
0#
#165
1#
#170
0#
#175
1#
#180
0#
#185
1#
#190
0#
#195
1#
#200
0#
#205
1#
#210
0#
#215
1#
#220
0#
#225
1#
#230
0#
b101 %
b101 '
b101 2
#235
1#
#240
b1 -
0,
0#
0)
0$
#245
1#
#248
0*
1+
b1 1
#250
0#
#255
1#
#258
0!
05
b101 3
#260
b10 -
1,
0#
1)
1$
#265
1#
#268
0,
b10 -
1*
b10 1
#270
0#
#275
1#
#278
1"
14
b100 3
#280
0#
#285
1#
#288
b11 3
#290
0#
#295
1#
#298
b10 3
#300
0#
#305
1#
#308
b0 -
1,
1(
b1 3
#310
0#
#315
1#
#318
x*
0+
b0 1
0(
b0 3
#320
0#
#325
1#
#328
0"
04
1!
15
