misc/sequence_detector/mprogram_synthesis.v
// riconoscitore di sequenze alternate 00, 01, 10 e 11, 01, 10, con 
// contatore su 4 bit di sequenze riconosciute 
module sequence_detector(reset_, clock, x1_x0, z3_z0);
	input reset_, clock;
	input[1:0] x1_x0;
	output[3:0] z3_z0;

	wire b0; // comando 
	wire[1:0] c1_c0; // condizionamento
	
	wire[1:0] mjr;

	data_path dp(reset_, clock, x1_x0, z3_z0, b0, c1_c0, mjr);
	control_unit cu(reset_, clock, b0, c1_c0, mjr);
endmodule;

module data_path(reset_, clock, x1_x0, z3_z0, b0, c1_c0, mjr);
	input reset_, clock;
	input[1:0] x1_x0;
	output[3:0] z3_z0;
	input b0;
	output[1:0] c1_c0;
	output[1:0] mjr;

	reg[3:0] COUNT;
	assign z3_z0 = COUNT;

	always @(reset_ == 0) #1 begin
		COUNT <= 0;	
	end

	always @(posedge clock) if(reset_ == 1) #3 begin
		// sarebbe un multiplexer 2 a 1 pilotato da b0
		case(b0)
			0: COUNT <= COUNT;
									 // sarebbe un multiplexer 2 a 1 pilotato da x1 & ~x0
			1: COUNT <= (x1_x0 == 'B10) ? COUNT + 1 : COUNT;
		endcase
	end

	assign c1_c0[1] = ({COUNT[0], x1_x0} == 'B000) | ({COUNT[0], x1_x0} == 'B111);
	assign c1_c0[0] = x1_x0 == 'B01;

	// questo non funziona con allineamento ai clock (c'e' un ciclo extra di
	// sincronizzazione per il MJR, in verita' non sarebbe il modello giusto
	// a prescindere...)
	assign mjr = c1_c0[0] ? 'B11 : c1_c0[1] ? 'B01 : 'B00; 
endmodule

module control_unit(reset_, clock, b0, c1_c0, mjr);
	input reset_, clock;
	output b0;
	input[1:0] c1_c0;
	input[1:0] mjr;

	reg[1:0] STAR;
	localparam
		s0 = 'B00,
		s1 = 'B01,
		s2 = 'B10,
		s3 = 'B11;

	reg[1:0] MJR;

	always @(reset_ == 0) #1 begin
		STAR <= s0;
	end

	// --- ROM ---
	wire m_b0 [0:3];
	wire eff [0:3];
	wire[1:0] addr_T [0:3];
	wire[1:0] addr_F [0:3];
	wire m_type [0:3];
	
	assign m_b0[0] = 'B0;
	assign m_b0[1] = 'B0;
	assign m_b0[2] = 'B0;
	assign m_b0[3] = 'B1;

	assign eff[0] = 'B1;
	assign eff[1] = 'B0;
	assign eff[2] = 'BX;
	assign eff[3] = 'B1;

	assign addr_T[0] = 'B01;
	assign addr_T[1] = 'B10;
	assign addr_T[2] = 'BXX;
	assign addr_T[3] = 'B01;
	
	assign addr_F[0] = 'B00;
	assign addr_F[1] = 'B10;
	assign addr_F[2] = 'BXX;
	assign addr_F[3] = 'B00;

	assign m_type[0] = 'B0;
	assign m_type[1] = 'B0;
	assign m_type[2] = 'B1;
	assign m_type[3] = 'B0;
	// -----------
	
	assign b0 = m_b0[STAR];

	wire c_eff;
	assign c_eff = c1_c0[eff[STAR]];

	wire[1:0] addr_N;
	assign addr_N = c_eff ? addr_T[STAR] : addr_F[STAR];

	always @(posedge clock) if(reset_ == 1) #3 begin
		MJR <= mjr;
		STAR <= m_type[STAR] ? MJR : addr_N;
	end
endmodule

misc/sequence_detector/testbench.v
module testbench();
	reg t_reset_, t_clock;
	reg[1:0] t_x1_x0;
	wire[3:0] t_z3_z0;

	sequence_detector seq_detector (
		.reset_(t_reset_), .clock(t_clock),
		.x1_x0(t_x1_x0), .z3_z0(t_z3_z0)
	);

	initial forever #5 t_clock = ~t_clock;

	initial begin
		$dumpfile("waveform.vcd");
		$dumpvars;

		t_clock = 0;
		t_reset_ = 1;

		#1;

		t_x1_x0 = 00;

		#10;
		
		t_x1_x0 = 01;

		#10;
		
		t_x1_x0 = 10;

		#10;

		t_x1_x0 = 11;

		#10;
		
		t_x1_x0 = 01;

		#10;
		
		t_x1_x0 = 10;

		#10;
		
		$finish;
	end
endmodule

misc/sequence_detector/waveform.vcd
$date
	Sun Jan  5 01:37:32 2025
$end
$version
	Icarus Verilog
$end
$timescale
	1s
$end
$scope module testbench $end
$var wire 4 ! t_z3_z0 [3:0] $end
$var reg 1 " t_clock $end
$var reg 1 # t_reset_ $end
$var reg 2 $ t_x1_x0 [1:0] $end
$scope module seq_detector $end
$var wire 1 " clock $end
$var wire 1 # reset_ $end
$var wire 2 % x1_x0 [1:0] $end
$var wire 4 & z3_z0 [3:0] $end
$var wire 2 ' mjr [1:0] $end
$var wire 2 ( c1_c0 [1:0] $end
$var wire 1 ) b0 $end
$scope module cu $end
$var wire 1 ) b0 $end
$var wire 1 " clock $end
$var wire 1 # reset_ $end
$var wire 2 * mjr [1:0] $end
$var wire 1 + c_eff $end
$var wire 2 , c1_c0 [1:0] $end
$var wire 2 - addr_N [1:0] $end
$var parameter 32 . s0 $end
$var parameter 32 / s1 $end
$var parameter 32 0 s2 $end
$var parameter 32 1 s3 $end
$var reg 2 2 MJR [1:0] $end
$var reg 2 3 STAR [1:0] $end
$upscope $end
$scope module dp $end
$var wire 1 ) b0 $end
$var wire 1 " clock $end
$var wire 1 # reset_ $end
$var wire 2 4 x1_x0 [1:0] $end
$var wire 4 5 z3_z0 [3:0] $end
$var wire 2 6 mjr [1:0] $end
$var wire 2 7 c1_c0 [1:0] $end
$var reg 4 8 COUNT [3:0] $end
$upscope $end
$upscope $end
$upscope $end
$enddefinitions $end
$comment Show the parameter values. $end
$dumpall
b11 1
b10 0
b1 /
b0 .
$end
#0
$dumpvars
bx 8
bx 7
bx 6
bx 5
bx 4
bx 3
bx 2
bx -
bx ,
x+
bx *
x)
bx (
bx '
bx &
bx %
bx $
1#
0"
bx !
$end
#1
1+
b1 -
0)
b0 3
b0 !
b0 &
b0 5
b0 8
b1 '
b1 *
b1 6
b10 (
b10 ,
b10 7
b0 $
b0 %
b0 4
#5
1"
#8
b10 -
0+
b1 3
b1 2
#10
0"
#11
b11 '
b11 *
b11 6
1+
b1 (
b1 ,
b1 7
b1 $
b1 %
b1 4
#15
1"
#18
bx -
x+
b10 3
b11 2
#20
0"
#21
b0 '
b0 *
b0 6
b0 (
b0 ,
b0 7
b10 $
b10 %
b10 4
#25
1"
#28
b0 -
1)
0+
b11 3
b0 2
#30
0"
#31
b11 $
b11 %
b11 4
#35
1"
#38
0)
b0 3
#40
0"
#41
b11 '
b11 *
b11 6
b1 (
b1 ,
b1 7
b1 $
b1 %
b1 4
#45
1"
#48
b11 2
#50
0"
#51
b0 '
b0 *
b0 6
b0 (
b0 ,
b0 7
b10 $
b10 %
b10 4
#55
1"
#58
b0 2
