altro/b2_counter.v
module b2_counter(eu, q, ei, clock, reset_);
  input clock, reset_;
  input ei;
  output eu, q;
  reg OUTR;
  assign q = OUTR;	
  wire a;
  assign {a, eu} = ({q, ei} == 'B00) ? 'B00:
                   ({q, ei} == 'B10) ? 'B10:
                   ({q, ei} == 'B01) ? 'B10:
                 /*({q, ei} == 'B11)*/ 'B01;
  always @(reset_ == 0) #1 OUTR <= 0;
  always @(posedge clock) if (reset_==1) #2 OUTR <= a;
endmodule

altro/testbench.v
module testbench();
	reg t_clock, t_reset_;
	reg t_ei;
	wire [3:0] t_eu;
	wire [3:0] t_q;

	b2_counter count_0 (
		.clock(t_clock), .reset_(t_reset_),
		.ei(t_ei),
		.eu(t_eu[0]), .q(t_q[0])
	);
	
	b2_counter count_1 (
		.clock(t_clock), .reset_(t_reset_),
		.ei(t_eu[0]),
		.eu(t_eu[1]), .q(t_q[1])
	);

	b2_counter count_2 (
		.clock(t_clock), .reset_(t_reset_),
		.ei(t_eu[1]),
		.eu(t_eu[2]), .q(t_q[2])
	);

	b2_counter count_3 (
		.clock(t_clock), .reset_(t_reset_),
		.ei(t_eu[2]),
		.eu(t_eu[3]), .q(t_q[3])
	);

	initial begin
    forever #5 t_clock = ~t_clock; 
	end

	initial begin
		$dumpfile("waveform.vcd");
		$dumpvars;	

		t_clock = 0;
		t_reset_ = 0;
		t_ei = 0;

		#10 

		t_reset_ = 1;
		t_ei = 1;

		#200;

		$finish;
	end
endmodule

altro/waveform.vcd
$date
	Tue Nov 19 00:25:26 2024
$end
$version
	Icarus Verilog
$end
$timescale
	1s
$end
$scope module testbench $end
$var wire 4 ! t_q [3:0] $end
$var wire 4 " t_eu [3:0] $end
$var reg 1 # t_clock $end
$var reg 1 $ t_ei $end
$var reg 1 % t_reset_ $end
$scope module count_0 $end
$var wire 1 # clock $end
$var wire 1 $ ei $end
$var wire 1 & q $end
$var wire 1 % reset_ $end
$var wire 1 ' eu $end
$var wire 1 ( a $end
$var reg 1 & OUTR $end
$upscope $end
$scope module count_1 $end
$var wire 1 # clock $end
$var wire 1 ) ei $end
$var wire 1 * q $end
$var wire 1 % reset_ $end
$var wire 1 + eu $end
$var wire 1 , a $end
$var reg 1 * OUTR $end
$upscope $end
$scope module count_2 $end
$var wire 1 # clock $end
$var wire 1 - ei $end
$var wire 1 . q $end
$var wire 1 % reset_ $end
$var wire 1 / eu $end
$var wire 1 0 a $end
$var reg 1 . OUTR $end
$upscope $end
$scope module count_3 $end
$var wire 1 # clock $end
$var wire 1 1 ei $end
$var wire 1 2 q $end
$var wire 1 % reset_ $end
$var wire 1 3 eu $end
$var wire 1 4 a $end
$var reg 1 2 OUTR $end
$upscope $end
$upscope $end
$enddefinitions $end
$comment Show the parameter values. $end
$dumpall
$end
#0
$dumpvars
x4
x3
x2
x1
x0
x/
x.
x-
x,
x+
x*
x)
x(
x'
x&
0%
0$
0#
bx "
bx !
$end
#1
03
04
01
0/
00
0-
0+
0,
0)
b0 "
0'
0(
0&
0*
0.
b0 !
02
#5
1#
#10
03
01
0/
0-
0+
1(
0)
b0 "
0'
0#
1$
1%
#15
1#
#17
03
01
0/
1,
0-
0+
1)
b1 "
1'
0(
b1 !
1&
#20
0#
#25
1#
#27
03
00
01
0/
0)
0-
0'
1(
b0 "
0+
1,
0&
b10 !
1*
#30
0#
#35
1#
#37
03
10
01
0/
1-
1+
0,
1)
b11 "
1'
0(
b11 !
1&
#40
0#
#45
1#
#47
04
03
0)
0-
01
0'
1(
0+
0,
b0 "
0/
10
0&
0*
b100 !
1.
#50
0#
#55
1#
#57
03
01
0/
10
1,
0-
0+
1)
b1 "
1'
0(
b101 !
1&
#60
0#
#65
1#
#67
04
03
01
0/
10
0)
0-
0'
1(
b0 "
0+
1,
0&
b110 !
1*
#70
0#
#75
1#
#77
14
03
11
1/
00
1-
1+
0,
1)
b111 "
1'
0(
b111 !
1&
#80
0#
#85
1#
#87
0)
0-
01
0'
1(
0+
0,
0/
00
b0 "
03
14
0&
0*
0.
b1000 !
12
#90
0#
#95
1#
#97
03
14
01
0/
1,
0-
0+
1)
b1 "
1'
0(
b1001 !
1&
#100
0#
#105
1#
#107
03
14
00
01
0/
0)
0-
0'
1(
b0 "
0+
1,
0&
b1010 !
1*
#110
0#
#115
1#
#117
03
14
10
01
0/
1-
1+
0,
1)
b11 "
1'
0(
b1011 !
1&
#120
0#
#125
1#
#127
03
14
0)
0-
01
0'
1(
0+
0,
b0 "
0/
10
0&
0*
b1100 !
1.
#130
0#
#135
1#
#137
03
14
01
0/
10
1,
0-
0+
1)
b1 "
1'
0(
b1101 !
1&
#140
0#
#145
1#
#147
03
14
01
0/
10
0)
0-
0'
1(
b0 "
0+
1,
0&
b1110 !
1*
#150
0#
#155
1#
#157
13
04
11
1/
00
1-
1+
0,
1)
b1111 "
1'
0(
b1111 !
1&
#160
0#
#165
1#
#167
0)
0-
01
0'
1(
0+
0,
0/
00
b0 "
03
04
0&
0*
0.
b0 !
02
#170
0#
#175
1#
#177
03
01
0/
1,
0-
0+
1)
b1 "
1'
0(
b1 !
1&
#180
0#
#185
1#
#187
03
00
01
0/
0)
0-
0'
1(
b0 "
0+
1,
0&
b10 !
1*
#190
0#
#195
1#
#197
03
10
01
0/
1-
1+
0,
1)
b11 "
1'
0(
b11 !
1&
#200
0#
#205
1#
#207
04
03
0)
0-
01
0'
1(
0+
0,
b0 "
0/
10
0&
0*
b100 !
1.
